keycloak_jwt_checker/__init__.py
keycloak_jwt_checker-1.0.0.dist-info/LICENSE
keycloak_jwt_checker-1.0.0.dist-info/METADATA
keycloak_jwt_checker-1.0.0.dist-info/WHEEL
keycloak_jwt_checker-1.0.0.dist-info/entry_points.txt
keycloak_jwt_checker-1.0.0.dist-info/RECORD
