Metadata-Version: 2.3
Name: keycloak-jwt-checker
Version: 1.0.0
Summary: 
License: MIT
Author: Max Pfeiffer
Author-email: max@maxpfeiffer.ch
Requires-Python: >=3.12,<4.0
Classifier: License :: OSI Approved :: MIT License
Classifier: Programming Language :: Python :: 3
Classifier: Programming Language :: Python :: 3.12
Classifier: Programming Language :: Python :: 3.13
Requires-Dist: click (>=8.1.8,<9.0.0)
Requires-Dist: pyjwt (>=2.10.1,<3.0.0)
Requires-Dist: python-keycloak (>=5.1.1,<6.0.0)
